[
  {"word": "Abate", "definition": "To reduce in intensity or amount"},
  {"word": "Aberrant", "definition": "Departing from the normal or expected"},
  {"word": "Abscond", "definition": "To leave hurriedly and secretly to escape"},
  {"word": "Abstemious", "definition": "Restrained in eating and drinking"},
  {"word": "Acrimony", "definition": "Bitterness or ill feeling in speech or manner"},
  {"word": "Acumen", "definition": "Keen insight and good judgment"},
  {"word": "Adulterate", "definition": "To make impure by adding inferior substances"},
  {"word": "Aesthetic", "definition": "Concerned with beauty or the appreciation of beauty"},
  {"word": "Alacrity", "definition": "Cheerful willingness and eagerness"},
  {"word": "Ambiguous", "definition": "Open to more than one interpretation"},
  {"word": "Ambivalent", "definition": "Having mixed or contradictory feelings about something"},
  {"word": "Ameliorate", "definition": "To make something bad better"},
  {"word": "Anachronism", "definition": "Something out of its proper historical time"},
  {"word": "Anecdote", "definition": "A short, amusing or interesting story about a real event"},
  {"word": "Antagonize", "definition": "To cause someone to become hostile"},
  {"word": "Apathy", "definition": "Lack of interest, enthusiasm, or concern"},
  {"word": "Appease", "definition": "To pacify by making concessions"},
  {"word": "Arcane", "definition": "Known only to a few; mysterious and obscure"},
  {"word": "Arduous", "definition": "Requiring strenuous effort; difficult"},
  {"word": "Articulate", "definition": "Expressing oneself clearly and effectively"},
  {"word": "Ascetic", "definition": "Practicing severe self-discipline and avoiding pleasure"},
  {"word": "Assiduous", "definition": "Showing great care and perseverance"},
  {"word": "Astute", "definition": "Having sharp insight and clever judgment"},
  {"word": "Audacious", "definition": "Showing willingness to take bold risks"},
  {"word": "Austere", "definition": "Severe or strict in manner; without comfort"},
  {"word": "Avarice", "definition": "Extreme greed for wealth or gain"},
  {"word": "Banal", "definition": "So lacking in originality as to be obvious and boring"},
  {"word": "Benevolent", "definition": "Well-meaning and kindly toward others"},
  {"word": "Bombastic", "definition": "High-sounding language with little meaning"},
  {"word": "Buoyant", "definition": "Cheerful and optimistic; able to stay afloat"},
  {"word": "Cacophony", "definition": "A harsh, unpleasant mixture of sounds"},
  {"word": "Candid", "definition": "Truthful and straightforward; frank"},
  {"word": "Capricious", "definition": "Given to sudden unpredictable changes"},
  {"word": "Castigate", "definition": "To reprimand or punish severely"},
  {"word": "Caustic", "definition": "Sarcastic in a scathing and bitter way"},
  {"word": "Chicanery", "definition": "The use of trickery to achieve one's purpose"},
  {"word": "Circumspect", "definition": "Wary and unwilling to take risks"},
  {"word": "Clandestine", "definition": "Kept secret or done secretively"},
  {"word": "Coerce", "definition": "To persuade using force or threats"},
  {"word": "Cogent", "definition": "Clear, logical, and convincing"},
  {"word": "Complacent", "definition": "Showing uncritical satisfaction with oneself"},
  {"word": "Concede", "definition": "To admit or acknowledge reluctantly"},
  {"word": "Convoluted", "definition": "Extremely complex and difficult to follow"},
  {"word": "Corroborate", "definition": "To confirm or support with evidence"},
  {"word": "Credulity", "definition": "Too great a readiness to believe things"},
  {"word": "Culpable", "definition": "Deserving blame for a fault or wrong"},
  {"word": "Cursory", "definition": "Hasty and therefore not thorough"},
  {"word": "Cynical", "definition": "Distrustful of human sincerity or integrity"},
  {"word": "Daunt", "definition": "To make someone feel intimidated or apprehensive"},
  {"word": "Debunk", "definition": "To expose the falseness of an idea or belief"},
  {"word": "Decorum", "definition": "Behavior in keeping with good taste and propriety"},
  {"word": "Deference", "definition": "Humble submission and respect toward another"},
  {"word": "Demagogue", "definition": "A leader who gains power by appealing to emotions over reason"},
  {"word": "Denounce", "definition": "To publicly declare to be wrong or evil"},
  {"word": "Derivative", "definition": "Imitative of the work of another; not original"},
  {"word": "Didactic", "definition": "Intended to teach, especially moralistically"},
  {"word": "Diffident", "definition": "Modest or shy due to a lack of self-confidence"},
  {"word": "Diligent", "definition": "Having or showing care and effort in one's work"},
  {"word": "Discern", "definition": "To recognize or find out with difficulty"},
  {"word": "Discordant", "definition": "Not in harmony; disagreeing"},
  {"word": "Dispassionate", "definition": "Not influenced by strong emotion; rational"},
  {"word": "Disparate", "definition": "Essentially different in kind; not able to be compared"},
  {"word": "Dissemble", "definition": "To conceal one's true motives or feelings"},
  {"word": "Divergent", "definition": "Tending to develop in different directions"},
  {"word": "Dogmatic", "definition": "Inclined to lay down principles as undeniably true"},
  {"word": "Dubious", "definition": "Hesitating or doubting; not reliable"},
  {"word": "Ebullient", "definition": "Cheerful and full of energy"},
  {"word": "Eccentric", "definition": "Unconventional and slightly strange behavior"},
  {"word": "Egregious", "definition": "Outstandingly bad; shocking"},
  {"word": "Eloquent", "definition": "Fluent and persuasive in speech or writing"},
  {"word": "Emulate", "definition": "To match or surpass by imitation"},
  {"word": "Enervate", "definition": "To weaken; drain of energy"},
  {"word": "Enigmatic", "definition": "Difficult to interpret or understand; mysterious"},
  {"word": "Ephemeral", "definition": "Lasting for a very short time"},
  {"word": "Equivocal", "definition": "Open to more than one interpretation; ambiguous"},
  {"word": "Erudite", "definition": "Having or showing great knowledge or learning"},
  {"word": "Esoteric", "definition": "Intended for a small group with specialized knowledge"},
  {"word": "Euphemism", "definition": "A mild word used in place of something harsh"},
  {"word": "Exacerbate", "definition": "To make a problem or bad situation worse"},
  {"word": "Exculpate", "definition": "To show that someone is not guilty"},
  {"word": "Exemplary", "definition": "Representing the best of its kind; serving as a model"},
  {"word": "Exhaustive", "definition": "Covering all aspects thoroughly and completely"},
  {"word": "Exonerate", "definition": "To officially clear someone from blame or fault"},
  {"word": "Expedient", "definition": "Convenient and practical though possibly improper"},
  {"word": "Facetious", "definition": "Treating serious issues with inappropriate humor"},
  {"word": "Fallacious", "definition": "Based on a mistaken belief; logically unsound"},
  {"word": "Fastidious", "definition": "Very attentive to accuracy and detail"},
  {"word": "Fatuous", "definition": "Silly and pointless in a self-satisfied way"},
  {"word": "Fervent", "definition": "Having or displaying intense passion or conviction"},
  {"word": "Furtive", "definition": "Attempting to avoid notice; secretive"},
  {"word": "Garrulous", "definition": "Excessively talkative, especially about trivial things"},
  {"word": "Gratuitous", "definition": "Uncalled for; lacking good reason"},
  {"word": "Gregarious", "definition": "Fond of company; sociable"},
  {"word": "Guile", "definition": "Sly or cunning intelligence used to deceive"},
  {"word": "Hapless", "definition": "Unfortunate and unlucky"},
  {"word": "Hegemony", "definition": "Leadership or dominance of one group over others"},
  {"word": "Heretical", "definition": "Holding beliefs contrary to accepted doctrine"},
  {"word": "Hubris", "definition": "Excessive pride or self-confidence"},
  {"word": "Iconoclast", "definition": "A person who attacks cherished beliefs or institutions"},
  {"word": "Idiosyncrasy", "definition": "A distinctive personal peculiarity"},
  {"word": "Ignominious", "definition": "Deserving or causing public disgrace"},
  {"word": "Impartial", "definition": "Treating all rivals equally; fair and just"},
  {"word": "Impetuous", "definition": "Acting quickly without thought or care"},
  {"word": "Implicit", "definition": "Suggested but not directly expressed"},
  {"word": "Impudent", "definition": "Not showing due respect; impertinent"},
  {"word": "Incisive", "definition": "Intelligently analytical and clear-thinking"},
  {"word": "Incongruous", "definition": "Not in harmony with the surroundings"},
  {"word": "Indolent", "definition": "Wanting to avoid activity or exertion; lazy"},
  {"word": "Ineffable", "definition": "Too great or extreme to be expressed in words"},
  {"word": "Ingenuous", "definition": "Innocent and unsuspecting; artless"},
  {"word": "Inimical", "definition": "Tending to obstruct or harm; hostile"},
  {"word": "Insipid", "definition": "Lacking flavor, vigor, or interest"},
  {"word": "Intransigent", "definition": "Unwilling to change one's views or agree to compromise"},
  {"word": "Inveterate", "definition": "Having a habit too firmly established to change"},
  {"word": "Irascible", "definition": "Having or showing a tendency to be easily angered"},
  {"word": "Kowtow", "definition": "To act in an excessively submissive way"},
  {"word": "Laconic", "definition": "Using very few words; brief and concise"},
  {"word": "Laud", "definition": "To praise highly, especially in public"},
  {"word": "Loquacious", "definition": "Tending to talk a great deal"},
  {"word": "Lucid", "definition": "Expressed clearly; easy to understand"},
  {"word": "Magnanimous", "definition": "Very generous or forgiving toward a rival"},
  {"word": "Malfeasance", "definition": "Wrongdoing, especially by a public official"},
  {"word": "Malleable", "definition": "Easily influenced; able to be reshaped"},
  {"word": "Maverick", "definition": "An independent-minded person who does not follow the crowd"},
  {"word": "Mendacious", "definition": "Not telling the truth; lying"},
  {"word": "Mercurial", "definition": "Subject to sudden or unpredictable changes of mood"},
  {"word": "Meticulous", "definition": "Showing great attention to detail and care"},
  {"word": "Misanthrope", "definition": "A person who dislikes humankind in general"},
  {"word": "Mitigate", "definition": "To make less severe, serious, or painful"},
  {"word": "Mollify", "definition": "To appease the anger or anxiety of someone"},
  {"word": "Morose", "definition": "Sullen and ill-tempered"},
  {"word": "Mundane", "definition": "Lacking interest or excitement; ordinary"},
  {"word": "Nebulous", "definition": "Not clear or defined; vague"},
  {"word": "Nefarious", "definition": "Wicked or criminal in nature"},
  {"word": "Obdurate", "definition": "Stubbornly refusing to change one's opinion"},
  {"word": "Obsequious", "definition": "Excessively eager to serve or please"},
  {"word": "Obstinate", "definition": "Stubbornly refusing to change despite argument"},
  {"word": "Obtuse", "definition": "Slow to understand; lacking sharpness of mind"},
  {"word": "Ominous", "definition": "Giving the impression that something bad is coming"},
  {"word": "Opaque", "definition": "Not able to be seen through; not transparent or clear"},
  {"word": "Ostracize", "definition": "To exclude from society or a group"},
  {"word": "Parsimonious", "definition": "Unwilling to spend money; extremely frugal"},
  {"word": "Patronize", "definition": "To treat with an air of superiority"},
  {"word": "Paucity", "definition": "The presence of something in only small amounts"},
  {"word": "Pedantic", "definition": "Overly concerned with minor details or rules"},
  {"word": "Perfidious", "definition": "Guilty of betrayal or deceit; treacherous"},
  {"word": "Peripheral", "definition": "Relating to the edge or outer part; not central"},
  {"word": "Pervasive", "definition": "Spreading widely throughout; prevalent"},
  {"word": "Petulant", "definition": "Childishly sulky or bad-tempered"},
  {"word": "Phlegmatic", "definition": "Having an unemotional and calm disposition"},
  {"word": "Placid", "definition": "Not easily upset or excited; calm"},
  {"word": "Platitude", "definition": "An overused remark that sounds meaningful but is not"},
  {"word": "Plausible", "definition": "Seeming reasonable or probable"},
  {"word": "Polemical", "definition": "Strongly attacking or defending a position"},
  {"word": "Pragmatic", "definition": "Dealing with things practically rather than theoretically"},
  {"word": "Presumptuous", "definition": "Overstepping due bounds; too bold or forward"},
  {"word": "Prevaricate", "definition": "To speak or act evasively; to avoid the truth"},
  {"word": "Pristine", "definition": "In its original condition; unspoiled"},
  {"word": "Prodigal", "definition": "Spending money recklessly; wastefully extravagant"},
  {"word": "Profligate", "definition": "Recklessly wasteful or extravagant"},
  {"word": "Proliferate", "definition": "To increase rapidly in number"},
  {"word": "Propitious", "definition": "Giving or indicating a good chance of success"},
  {"word": "Prudent", "definition": "Acting with care and thought for the future"},
  {"word": "Querulous", "definition": "Complaining in a petty or whining manner"},
  {"word": "Quixotic", "definition": "Exceedingly idealistic and unrealistic"},
  {"word": "Recalcitrant", "definition": "Stubbornly resistant to authority or discipline"},
  {"word": "Reclusive", "definition": "Avoiding the company of other people"},
  {"word": "Reconcile", "definition": "To restore friendly relations between"},
  {"word": "Recondite", "definition": "Not known by many people; obscure"},
  {"word": "Rectify", "definition": "To put right; to correct"},
  {"word": "Redress", "definition": "To remedy or set right an undesirable situation"},
  {"word": "Refute", "definition": "To prove a statement or person to be wrong"},
  {"word": "Relegate", "definition": "To assign to a lower position or less important role"},
  {"word": "Repudiate", "definition": "To refuse to accept or be associated with"},
  {"word": "Reticent", "definition": "Not revealing one's thoughts or feelings readily"},
  {"word": "Rhetoric", "definition": "Language designed to have a persuasive effect"},
  {"word": "Sagacious", "definition": "Having good judgment; wise"},
  {"word": "Salient", "definition": "Most noticeable or important; prominent"},
  {"word": "Sanctimonious", "definition": "Making a show of being morally superior"},
  {"word": "Skeptical", "definition": "Not easily convinced; having doubts"},
  {"word": "Solicitous", "definition": "Showing great care and concern for someone"},
  {"word": "Soporific", "definition": "Tending to induce sleep; tediously boring"},
  {"word": "Spurious", "definition": "Not genuine or authentic; false"},
  {"word": "Stagnant", "definition": "Showing no activity; dull and static"},
  {"word": "Stoic", "definition": "Enduring pain or hardship without complaint"},
  {"word": "Strident", "definition": "Loud and harsh; presenting a point of view forcefully"},
  {"word": "Subjugate", "definition": "To bring under domination or control"},
  {"word": "Subtle", "definition": "So delicate or precise as to be difficult to analyze"},
  {"word": "Supercilious", "definition": "Behaving as though one is superior to others"},
  {"word": "Surreptitious", "definition": "Kept secret due to being improper or unauthorized"},
  {"word": "Sycophant", "definition": "A person who flatters powerful people for personal gain"},
  {"word": "Taciturn", "definition": "Reserved or uncommunicative in speech"},
  {"word": "Tenacious", "definition": "Persistent and determined; not giving up easily"},
  {"word": "Terse", "definition": "Sparing in the use of words; abrupt"},
  {"word": "Timorous", "definition": "Showing or suffering from nervousness or fear"},
  {"word": "Torpid", "definition": "Mentally or physically inactive; lethargic"},
  {"word": "Transient", "definition": "Lasting only for a short time; impermanent"},
  {"word": "Trite", "definition": "Overused and lacking originality"},
  {"word": "Truculent", "definition": "Eager or quick to argue or fight; aggressively defiant"},
  {"word": "Turbid", "definition": "Cloudy or muddy; not clear"},
  {"word": "Umbrage", "definition": "Offense or annoyance at something"},
  {"word": "Underscore", "definition": "To emphasize or draw attention to"},
  {"word": "Unequivocal", "definition": "Leaving no doubt; unambiguous"},
  {"word": "Vacillate", "definition": "To waver between different opinions or actions"},
  {"word": "Venerate", "definition": "To regard with great respect and reverence"},
  {"word": "Verbose", "definition": "Using more words than needed; wordy"},
  {"word": "Vex", "definition": "To make someone feel annoyed or frustrated"},
  {"word": "Vigilant", "definition": "Keeping careful watch for possible danger"},
  {"word": "Vindicate", "definition": "To clear someone of blame or suspicion"},
  {"word": "Virulent", "definition": "Extremely harmful or malicious in effect"},
  {"word": "Volatile", "definition": "Liable to change rapidly and unpredictably"},
  {"word": "Wane", "definition": "To decrease in vigor, power, or extent"},
  {"word": "Wary", "definition": "Feeling or showing caution about danger"},
  {"word": "Zealous", "definition": "Having or showing great energy in pursuit of a cause"}
]